{"tag":"-eer","count":39,"results":[{"word":"auctioneer","explain":"n. 拍卖人"},{"word":"beer","explain":"n.啤酒"},{"word":"buccaneer","explain":"n. 海盗"},{"word":"bucketeer","explain":"买空卖空者，投机家"},{"word":"career","explain":"n.生涯，职业，经历"},{"word":"chanticleer","explain":"n. 雄鸡，公鸡"},{"word":"charioteer","explain":"n. 战车的御者"},{"word":"cheer","explain":"vt.使振作；欢呼"},{"word":"commandeer","explain":"vt. 征募,霸占"},{"word":"compeer","explain":"n. 地位相等的人,同辈,伙伴"},{"word":"deer","explain":"n.鹿"},{"word":"domineer","explain":"v. 擅权，作威作福"},{"word":"electioneer","explain":"vi. 从事选举活动"},{"word":"engineer","explain":"n.工程师，技师"},{"word":"gazetteer","explain":"n. 地名词典，地名表"},{"word":"jeer","explain":"v. 嘲笑"},{"word":"leer","explain":"v. 斜眼看，睨视"},{"word":"manufactureer","explain":"n.制造商；制造厂"},{"word":"marketeer","explain":"市场上的卖主，市场商人"},{"word":"mountaineer","explain":"n. 登山家,山地人"},{"word":"muleteer","explain":" n. 骡夫"},{"word":"musketeer","explain":"n. 持步枪的士兵,步兵"},{"word":"mutineer","explain":"n. 反叛者，背叛者"},{"word":"overseer","explain":"n. 监督,工头"},{"word":"pamphleteer","explain":"n. 小册子作者,檄文执笔者"},{"word":"peer","explain":"vi.凝视；隐约出现"},{"word":"pioneer","explain":"n.先锋"},{"word":"privateer","explain":"n. 私有武装船,私掠船"},{"word":"profiteer","explain":"n. 奸商，牟取暴利者"},{"word":"queer","explain":"a.奇怪的，古怪的"},{"word":"racketeer","explain":"n. 讹诈钱财的歹徒"},{"word":"reindeer","explain":"n. 驯鹿"},{"word":"seer","explain":"n. 预言者,先知,幻想家"},{"word":"sheer","explain":"a.纯粹的；全然的"},{"word":"sneer","explain":"vi.&n.冷笑；嘲笑"},{"word":"steer","explain":"vt.&vi.驾驶"},{"word":"veer","explain":"v. 转向，改变（话题等）"},{"word":"veneer","explain":"n. （镶于劣质东西上的）镶面板，外表"},{"word":"volunteer","explain":"n.志愿者 vt.志愿"}]}